SPYGE/__init__.py
SPYGE/main.py
SPYGE-0.0.4.dist-info/METADATA
SPYGE-0.0.4.dist-info/WHEEL
SPYGE-0.0.4.dist-info/top_level.txt
SPYGE-0.0.4.dist-info/RECORD
