Metadata-Version: 2.1
Name: SPYGE
Version: 0.0.4
Summary: A very simple graphics library based on tkinter.
Home-page: https://github.com/matetonny/SPYGE
Author: mate_tonny
Author-email: matechocheli2@gmail.com
Project-URL: Bug Tracker, https://github.com/matetonny/SPYGE/issues
Classifier: Programming Language :: Python :: 3
Classifier: License :: OSI Approved :: MIT License
Classifier: Operating System :: OS Independent
Requires-Python: >=3.6
